{
  "schema_version": "deeputin-calibration-seven-datasets-v7",
  "dataset_id": "person_01",
  "record_id": "frame_000301",
  "source_path": "/Users/victorkhudyakov/myproject/dataset/calibration_dataset/photos/person_01/frame_000301.jpg",
  "source_filename": "frame_000301.jpg",
  "source_sha256": "ed0977043c6456b9f044cf76687a19b5549700b69c94e3e55c7ae225066032c9",
  "frame_index": 301,
  "sequence_id": "person_01",
  "pose": {
    "yaw": 17.210371017456055,
    "pitch": -1.9069968461990356,
    "roll": 2.189136505126953
  },
  "pose_bin": "right_light",
  "canonical_yaw": 17.5,
  "alignment": {
    "raw": "3DDFA object-space landmarks before pose/translation/camera",
    "aligned": "full-mesh normalized object-space landmarks rotated to pose-bin canonical yaw"
  },
  "arrays": {
    "angle_deg_pitch_yaw_roll": [
      -1.9069968461990356,
      17.210371017456055,
      2.189136505126953
    ],
    "rotation_row_matrix": [
      [
        0.9545276761054993,
        0.03648801147937775,
        -0.2958809733390808
      ],
      [
        -0.048016104847192764,
        0.9983406662940979,
        -0.031787239015102386
      ],
      [
        0.2942301332950592,
        0.04454885423183441,
        0.9546957612037659
      ]
    ],
    "translation": [
      -0.057376645505428314,
      0.034065958112478256,
      1.3471368551254272
    ],
    "object_normalization_center": [
      0.008243032731115818,
      0.006721843965351582,
      0.01684861071407795
    ],
    "object_normalization_scale": [
      0.588411271572113
    ],
    "canonical_rotation_row_matrix": [
      [
        0.9537169337272644,
        0.0,
        -0.30070579051971436
      ],
      [
        0.0,
        1.0,
        0.0
      ],
      [
        0.30070579051971436,
        0.0,
        0.9537169337272644
      ]
    ],
    "canonical_yaw": [
      17.5
    ],
    "ldm106_visible_original": [
      1,
      1,
      1,
      1,
      1,
      0,
      0,
      0,
      0,
      0,
      0,
      0,
      1,
      1,
      1,
      0,
      1,
      0,
      0,
      0,
      0,
      0,
      0,
      0,
      0,
      0,
      0,
      0,
      0,
      0,
      0,
      0,
      0,
      1,
      1,
      1,
      1,
      1,
      1,
      1,
      1,
      1,
      1,
      1,
      1,
      0,
      0,
      1,
      1,
      1,
      1,
      1,
      1,
      1,
      1,
      1,
      1,
      1,
      1,
      1,
      1,
      1,
      1,
      0,
      0,
      0,
      0,
      1,
      0,
      0,
      1,
      0,
      0,
      1,
      0,
      1,
      0,
      0,
      0,
      0,
      0,
      0,
      0,
      0,
      1,
      1,
      1,
      1,
      1,
      0,
      1,
      1,
      1,
      1,
      1,
      1,
      0,
      1,
      1,
      1,
      0,
      1,
      1,
      1,
      0,
      0
    ],
    "ldm134_visible_original": [
      0,
      0,
      0,
      1,
      0,
      0,
      1,
      1,
      1,
      0,
      0,
      0,
      1,
      1,
      1,
      1,
      1,
      1,
      1,
      1,
      1,
      1,
      0,
      0,
      0,
      1,
      0,
      0,
      0,
      1,
      0,
      0,
      1,
      0,
      1,
      0,
      1,
      1,
      1,
      1,
      0,
      1,
      0,
      0,
      1,
      1,
      1,
      1,
      1,
      1,
      1,
      1,
      1,
      1,
      1,
      1,
      1,
      1,
      0,
      0,
      1,
      1,
      1,
      1,
      1,
      1,
      1,
      1,
      1,
      1,
      1,
      1,
      1,
      1,
      1,
      1,
      1,
      1,
      1,
      1,
      1,
      1,
      0,
      1,
      1,
      1,
      1,
      0,
      1,
      1,
      1,
      1,
      1,
      1,
      1,
      1,
      0,
      1,
      1,
      1,
      1,
      1,
      0,
      0,
      1,
      1,
      1,
      1,
      1,
      1,
      1,
      1,
      1,
      1,
      1,
      1,
      1,
      1,
      1,
      1,
      1,
      1,
      1,
      1,
      1,
      1,
      1,
      1,
      1,
      1,
      1,
      1,
      1,
      1
    ]
  },
  "files": {
    "ldm106_raw": "ldm106_raw.csv",
    "ldm106_aligned": "ldm106_aligned.csv",
    "ldm134_raw": "ldm134_raw.csv",
    "ldm134_aligned": "ldm134_aligned.csv",
    "metadata": "metadata.json",
    "npz": "record.npz"
  }
}