{
  "schema_version": "deeputin-calibration-seven-datasets-v7",
  "dataset_id": "person_06",
  "record_id": "frame_0079",
  "source_path": "/Users/victorkhudyakov/myproject/dataset/calibration_dataset/photos/person_06/frame_0079.jpg",
  "source_filename": "frame_0079.jpg",
  "source_sha256": "2d1d84f406a1cdb0a9654cbc7e56234a56d5dcbec032b64c6495ea40575e8d35",
  "frame_index": 79,
  "sequence_id": "person_06",
  "pose": {
    "yaw": -1.3851685523986816,
    "pitch": -2.6260056495666504,
    "roll": 5.466034889221191
  },
  "pose_bin": "frontal",
  "canonical_yaw": 0.0,
  "alignment": {
    "raw": "3DDFA object-space landmarks before pose/translation/camera",
    "aligned": "full-mesh normalized object-space landmarks rotated to pose-bin canonical yaw"
  },
  "arrays": {
    "angle_deg_pitch_yaw_roll": [
      -2.6260056495666504,
      -1.3851685523986816,
      5.466034889221191
    ],
    "rotation_row_matrix": [
      [
        0.9951618909835815,
        0.09522783011198044,
        0.024173399433493614
      ],
      [
        -0.09405313432216644,
        0.9945129752159119,
        -0.0458030141890049
      ],
      [
        -0.028402483090758324,
        0.0433078296482563,
        0.9986579418182373
      ]
    ],
    "translation": [
      -0.007401859387755394,
      -0.017536066472530365,
      1.668436884880066
    ],
    "object_normalization_center": [
      0.002012789249420166,
      0.008950679562985897,
      0.01263740286231041
    ],
    "object_normalization_scale": [
      0.5704192519187927
    ],
    "canonical_rotation_row_matrix": [
      [
        1.0,
        0.0,
        0.0
      ],
      [
        0.0,
        1.0,
        0.0
      ],
      [
        0.0,
        0.0,
        1.0
      ]
    ],
    "canonical_yaw": [
      0.0
    ],
    "ldm106_visible_original": [
      1,
      1,
      0,
      0,
      0,
      0,
      0,
      0,
      0,
      0,
      0,
      0,
      1,
      1,
      1,
      1,
      1,
      1,
      1,
      0,
      0,
      0,
      0,
      0,
      0,
      0,
      0,
      0,
      0,
      1,
      0,
      1,
      1,
      0,
      1,
      1,
      1,
      1,
      1,
      1,
      1,
      1,
      1,
      1,
      1,
      1,
      1,
      1,
      1,
      1,
      1,
      1,
      1,
      1,
      1,
      0,
      0,
      0,
      1,
      1,
      1,
      1,
      1,
      0,
      0,
      1,
      0,
      1,
      0,
      0,
      0,
      0,
      1,
      1,
      1,
      1,
      1,
      0,
      1,
      0,
      1,
      1,
      1,
      1,
      1,
      1,
      1,
      1,
      1,
      1,
      1,
      1,
      1,
      1,
      1,
      1,
      0,
      0,
      0,
      0,
      1,
      0,
      0,
      1,
      1,
      1
    ],
    "ldm134_visible_original": [
      1,
      1,
      1,
      1,
      1,
      0,
      1,
      1,
      0,
      0,
      0,
      0,
      1,
      1,
      1,
      0,
      0,
      0,
      1,
      1,
      1,
      1,
      1,
      0,
      1,
      1,
      1,
      1,
      1,
      1,
      1,
      1,
      1,
      1,
      1,
      1,
      1,
      1,
      0,
      0,
      0,
      1,
      1,
      1,
      0,
      0,
      1,
      1,
      1,
      1,
      1,
      1,
      1,
      1,
      1,
      1,
      1,
      1,
      1,
      1,
      1,
      1,
      1,
      1,
      1,
      1,
      1,
      1,
      1,
      1,
      1,
      1,
      1,
      1,
      1,
      1,
      1,
      1,
      1,
      1,
      1,
      1,
      1,
      1,
      1,
      1,
      1,
      0,
      1,
      0,
      0,
      0,
      0,
      0,
      0,
      0,
      0,
      0,
      0,
      0,
      0,
      0,
      1,
      1,
      0,
      0,
      1,
      0,
      1,
      1,
      1,
      0,
      0,
      0,
      0,
      0,
      0,
      0,
      0,
      1,
      1,
      1,
      1,
      1,
      1,
      1,
      1,
      1,
      1,
      1,
      1,
      1,
      0,
      0
    ]
  },
  "files": {
    "ldm106_raw": "ldm106_raw.csv",
    "ldm106_aligned": "ldm106_aligned.csv",
    "ldm134_raw": "ldm134_raw.csv",
    "ldm134_aligned": "ldm134_aligned.csv",
    "metadata": "metadata.json",
    "npz": "record.npz"
  }
}