{
  "schema_version": "deeputin-calibration-seven-datasets-v7",
  "dataset_id": "person_02",
  "record_id": "frame_000131",
  "source_path": "/Users/victorkhudyakov/myproject/dataset/calibration_dataset/photos/person_02/frame_000131.jpg",
  "source_filename": "frame_000131.jpg",
  "source_sha256": "08c5e6066c9adb5d4aa6adf0daed9a4d52c85acefa3697e06ccd66a0e6f638f5",
  "frame_index": 131,
  "sequence_id": "person_02",
  "pose": {
    "yaw": 71.28478240966797,
    "pitch": -4.715075492858887,
    "roll": -2.136637926101685
  },
  "pose_bin": "right_profile",
  "canonical_yaw": 70.0,
  "alignment": {
    "raw": "3DDFA object-space landmarks before pose/translation/camera",
    "aligned": "full-mesh normalized object-space landmarks rotated to pose-bin canonical yaw"
  },
  "arrays": {
    "angle_deg_pitch_yaw_roll": [
      -4.715075492858887,
      71.28478240966797,
      -2.1366379261016846
    ],
    "rotation_row_matrix": [
      [
        0.320641428232193,
        -0.011962703429162502,
        -0.9471251368522644
      ],
      [
        -0.04064370319247246,
        0.9988254904747009,
        -0.02637529745697975
      ],
      [
        0.946328341960907,
        0.04695168510079384,
        0.3197786211967468
      ]
    ],
    "translation": [
      -0.08986151218414307,
      -0.002024189569056034,
      1.0415377616882324
    ],
    "object_normalization_center": [
      -0.0002520544221624732,
      0.003739652456715703,
      9.732822945807129e-05
    ],
    "object_normalization_scale": [
      0.6515294909477234
    ],
    "canonical_rotation_row_matrix": [
      [
        0.3420201539993286,
        0.0,
        -0.9396926164627075
      ],
      [
        0.0,
        1.0,
        0.0
      ],
      [
        0.9396926164627075,
        0.0,
        0.3420201539993286
      ]
    ],
    "canonical_yaw": [
      70.0
    ],
    "ldm106_visible_original": [
      1,
      1,
      1,
      1,
      1,
      1,
      1,
      1,
      1,
      1,
      1,
      1,
      1,
      1,
      1,
      1,
      1,
      0,
      0,
      0,
      0,
      0,
      0,
      0,
      0,
      0,
      0,
      0,
      0,
      0,
      0,
      0,
      0,
      1,
      1,
      1,
      1,
      1,
      1,
      1,
      1,
      1,
      0,
      0,
      0,
      0,
      0,
      0,
      0,
      0,
      0,
      1,
      1,
      1,
      1,
      1,
      1,
      1,
      1,
      1,
      1,
      0,
      0,
      0,
      0,
      0,
      0,
      1,
      0,
      0,
      0,
      1,
      1,
      1,
      1,
      0,
      0,
      0,
      0,
      0,
      0,
      0,
      0,
      0,
      1,
      1,
      1,
      1,
      0,
      0,
      0,
      0,
      1,
      1,
      1,
      1,
      0,
      1,
      1,
      0,
      0,
      1,
      1,
      1,
      1,
      0
    ],
    "ldm134_visible_original": [
      1,
      1,
      1,
      1,
      1,
      1,
      0,
      0,
      1,
      0,
      0,
      0,
      1,
      1,
      1,
      1,
      0,
      0,
      0,
      0,
      0,
      0,
      0,
      0,
      0,
      0,
      0,
      0,
      0,
      0,
      0,
      0,
      0,
      0,
      0,
      0,
      0,
      0,
      0,
      0,
      0,
      0,
      0,
      0,
      1,
      1,
      1,
      1,
      1,
      1,
      1,
      1,
      1,
      1,
      1,
      1,
      1,
      0,
      0,
      0,
      0,
      0,
      0,
      0,
      0,
      0,
      0,
      0,
      0,
      0,
      1,
      1,
      1,
      1,
      1,
      1,
      1,
      1,
      1,
      0,
      0,
      0,
      0,
      0,
      0,
      0,
      0,
      0,
      1,
      1,
      1,
      1,
      0,
      1,
      0,
      1,
      0,
      0,
      0,
      0,
      0,
      0,
      0,
      0,
      1,
      1,
      1,
      1,
      1,
      1,
      1,
      1,
      1,
      0,
      0,
      0,
      0,
      0,
      0,
      1,
      0,
      1,
      1,
      1,
      1,
      1,
      1,
      1,
      1,
      0,
      0,
      0,
      0,
      0
    ]
  },
  "files": {
    "ldm106_raw": "ldm106_raw.csv",
    "ldm106_aligned": "ldm106_aligned.csv",
    "ldm134_raw": "ldm134_raw.csv",
    "ldm134_aligned": "ldm134_aligned.csv",
    "metadata": "metadata.json",
    "npz": "record.npz"
  }
}