{
  "schema_version": "deeputin-calibration-seven-datasets-v7",
  "dataset_id": "person_04",
  "record_id": "frame_000175",
  "source_path": "/Users/victorkhudyakov/myproject/dataset/calibration_dataset/photos/person_04/frame_000175.jpg",
  "source_filename": "frame_000175.jpg",
  "source_sha256": "f515c8d3dda4a511a913865420b6862f5ae2d9cd4c6c4def1e45069027e51028",
  "frame_index": 175,
  "sequence_id": "person_04",
  "pose": {
    "yaw": -7.439639091491699,
    "pitch": 0.1782091706991195,
    "roll": 2.2904508113861084
  },
  "pose_bin": "frontal",
  "canonical_yaw": 0.0,
  "alignment": {
    "raw": "3DDFA object-space landmarks before pose/translation/camera",
    "aligned": "full-mesh normalized object-space landmarks rotated to pose-bin canonical yaw"
  },
  "arrays": {
    "angle_deg_pitch_yaw_roll": [
      0.17820917069911957,
      -7.439639091491699,
      2.2904508113861084
    ],
    "rotation_row_matrix": [
      [
        0.9907895922660828,
        0.039628829807043076,
        0.12948164343833923
      ],
      [
        -0.040367480367422104,
        0.9991801381111145,
        0.0030841485131531954
      ],
      [
        -0.12925326824188232,
        -0.008282589726150036,
        0.9915770292282104
      ]
    ],
    "translation": [
      -0.010995283722877502,
      -0.016431577503681183,
      1.1461873054504395
    ],
    "object_normalization_center": [
      0.0022209493909031153,
      0.007017430383712053,
      0.006716209929436445
    ],
    "object_normalization_scale": [
      0.5921550989151001
    ],
    "canonical_rotation_row_matrix": [
      [
        1.0,
        0.0,
        0.0
      ],
      [
        0.0,
        1.0,
        0.0
      ],
      [
        0.0,
        0.0,
        1.0
      ]
    ],
    "canonical_yaw": [
      0.0
    ],
    "ldm106_visible_original": [
      1,
      0,
      0,
      0,
      0,
      0,
      0,
      0,
      0,
      0,
      0,
      0,
      0,
      1,
      1,
      1,
      1,
      0,
      1,
      0,
      0,
      0,
      0,
      0,
      0,
      0,
      0,
      0,
      0,
      1,
      0,
      1,
      1,
      1,
      1,
      1,
      1,
      1,
      1,
      1,
      1,
      1,
      1,
      1,
      1,
      0,
      1,
      1,
      1,
      1,
      1,
      1,
      1,
      1,
      1,
      0,
      0,
      0,
      1,
      1,
      1,
      1,
      1,
      1,
      0,
      1,
      0,
      1,
      0,
      1,
      1,
      1,
      1,
      1,
      1,
      1,
      1,
      0,
      1,
      0,
      0,
      1,
      1,
      1,
      1,
      1,
      1,
      1,
      1,
      0,
      1,
      1,
      1,
      1,
      1,
      1,
      0,
      1,
      1,
      1,
      0,
      1,
      1,
      1,
      1,
      1
    ],
    "ldm134_visible_original": [
      0,
      0,
      0,
      1,
      1,
      1,
      1,
      1,
      1,
      0,
      0,
      0,
      1,
      1,
      1,
      0,
      0,
      0,
      0,
      1,
      1,
      1,
      1,
      0,
      0,
      1,
      0,
      1,
      1,
      1,
      1,
      0,
      0,
      0,
      1,
      1,
      1,
      1,
      0,
      0,
      0,
      1,
      1,
      1,
      1,
      1,
      1,
      1,
      1,
      1,
      1,
      1,
      0,
      1,
      1,
      1,
      1,
      1,
      1,
      1,
      1,
      1,
      1,
      1,
      1,
      1,
      1,
      1,
      1,
      1,
      1,
      1,
      1,
      1,
      1,
      1,
      1,
      1,
      1,
      1,
      1,
      1,
      0,
      0,
      0,
      0,
      1,
      0,
      1,
      1,
      1,
      1,
      1,
      1,
      1,
      1,
      1,
      1,
      1,
      1,
      1,
      1,
      1,
      0,
      1,
      1,
      1,
      1,
      1,
      1,
      1,
      1,
      1,
      1,
      1,
      1,
      0,
      1,
      1,
      1,
      1,
      1,
      1,
      1,
      1,
      1,
      1,
      1,
      1,
      1,
      1,
      1,
      1,
      1
    ]
  },
  "files": {
    "ldm106_raw": "ldm106_raw.csv",
    "ldm106_aligned": "ldm106_aligned.csv",
    "ldm134_raw": "ldm134_raw.csv",
    "ldm134_aligned": "ldm134_aligned.csv",
    "metadata": "metadata.json",
    "npz": "record.npz"
  }
}