{
  "schema_version": "deeputin-calibration-seven-datasets-v7",
  "dataset_id": "person_05",
  "record_id": "frame_000377",
  "source_path": "/Users/victorkhudyakov/myproject/dataset/calibration_dataset/photos/person_05/frame_000377.jpg",
  "source_filename": "frame_000377.jpg",
  "source_sha256": "eaa16d0f52544b189dbb0b4dbef4fada1a13f918947b47997acd3ada01535929",
  "frame_index": 377,
  "sequence_id": "person_05",
  "pose": {
    "yaw": 53.99771499633789,
    "pitch": 1.6771159172058103,
    "roll": 3.741144895553589
  },
  "pose_bin": "right_profile",
  "canonical_yaw": 70.0,
  "alignment": {
    "raw": "3DDFA object-space landmarks before pose/translation/camera",
    "aligned": "full-mesh normalized object-space landmarks rotated to pose-bin canonical yaw"
  },
  "arrays": {
    "angle_deg_pitch_yaw_roll": [
      1.6771159172058105,
      53.99771499633789,
      3.741144895553589
    ],
    "rotation_row_matrix": [
      [
        0.586564838886261,
        0.038354452699422836,
        -0.8089935779571533
      ],
      [
        -0.04159458726644516,
        0.9989864230155945,
        0.017203664407134056
      ],
      [
        0.8088334202766418,
        0.023558689281344414,
        0.5875656604766846
      ]
    ],
    "translation": [
      -0.0672946572303772,
      -0.008535469882190228,
      0.6122694611549377
    ],
    "object_normalization_center": [
      0.003034200519323349,
      0.010021695867180824,
      0.0019605248235166073
    ],
    "object_normalization_scale": [
      0.6651427149772644
    ],
    "canonical_rotation_row_matrix": [
      [
        0.3420201539993286,
        0.0,
        -0.9396926164627075
      ],
      [
        0.0,
        1.0,
        0.0
      ],
      [
        0.9396926164627075,
        0.0,
        0.3420201539993286
      ]
    ],
    "canonical_yaw": [
      70.0
    ],
    "ldm106_visible_original": [
      1,
      1,
      1,
      1,
      1,
      1,
      1,
      1,
      1,
      1,
      1,
      1,
      1,
      1,
      1,
      0,
      1,
      0,
      0,
      0,
      0,
      0,
      0,
      0,
      0,
      0,
      0,
      0,
      0,
      0,
      0,
      0,
      0,
      1,
      1,
      1,
      1,
      1,
      1,
      1,
      1,
      1,
      1,
      1,
      1,
      0,
      0,
      0,
      1,
      1,
      0,
      1,
      1,
      1,
      1,
      1,
      1,
      1,
      1,
      1,
      1,
      0,
      0,
      0,
      0,
      0,
      0,
      1,
      0,
      0,
      1,
      0,
      1,
      1,
      1,
      0,
      0,
      0,
      1,
      0,
      0,
      0,
      0,
      1,
      1,
      1,
      1,
      1,
      1,
      0,
      0,
      0,
      1,
      1,
      1,
      1,
      0,
      1,
      1,
      1,
      0,
      1,
      1,
      1,
      1,
      1
    ],
    "ldm134_visible_original": [
      1,
      1,
      0,
      1,
      1,
      0,
      0,
      1,
      1,
      0,
      1,
      0,
      0,
      0,
      1,
      1,
      1,
      1,
      0,
      1,
      0,
      1,
      0,
      0,
      0,
      1,
      0,
      0,
      0,
      0,
      0,
      0,
      0,
      0,
      0,
      0,
      0,
      1,
      0,
      0,
      0,
      0,
      0,
      0,
      1,
      1,
      1,
      1,
      1,
      1,
      1,
      1,
      1,
      1,
      1,
      1,
      1,
      0,
      0,
      0,
      0,
      0,
      1,
      1,
      0,
      0,
      1,
      1,
      1,
      0,
      1,
      1,
      1,
      1,
      1,
      1,
      1,
      1,
      1,
      1,
      0,
      0,
      0,
      0,
      0,
      0,
      0,
      0,
      1,
      1,
      1,
      1,
      1,
      1,
      1,
      0,
      0,
      1,
      0,
      0,
      0,
      0,
      0,
      0,
      0,
      1,
      1,
      1,
      1,
      1,
      1,
      1,
      1,
      0,
      0,
      0,
      0,
      0,
      0,
      1,
      1,
      1,
      1,
      1,
      1,
      1,
      1,
      1,
      1,
      1,
      0,
      0,
      0,
      0
    ]
  },
  "files": {
    "ldm106_raw": "ldm106_raw.csv",
    "ldm106_aligned": "ldm106_aligned.csv",
    "ldm134_raw": "ldm134_raw.csv",
    "ldm134_aligned": "ldm134_aligned.csv",
    "metadata": "metadata.json",
    "npz": "record.npz"
  }
}