{
  "schema_version": "deeputin-calibration-seven-datasets-v7",
  "dataset_id": "person_01",
  "record_id": "frame_000281",
  "source_path": "/Users/victorkhudyakov/myproject/dataset/calibration_dataset/photos/person_01/frame_000281.jpg",
  "source_filename": "frame_000281.jpg",
  "source_sha256": "71380c6a97b7f434f63e01debd1c88679b1aba1a516039f2c523c024dd70b235",
  "frame_index": 281,
  "sequence_id": "person_01",
  "pose": {
    "yaw": -0.6800326108932495,
    "pitch": 1.4975972175598145,
    "roll": 1.2014983892440796
  },
  "pose_bin": "frontal",
  "canonical_yaw": 0.0,
  "alignment": {
    "raw": "3DDFA object-space landmarks before pose/translation/camera",
    "aligned": "full-mesh normalized object-space landmarks rotated to pose-bin canonical yaw"
  },
  "arrays": {
    "angle_deg_pitch_yaw_roll": [
      1.4975972175598145,
      -0.6800326108932495,
      1.2014983892440796
    ],
    "rotation_row_matrix": [
      [
        0.9997096657752991,
        0.020967090502381325,
        0.011868529953062534
      ],
      [
        -0.021271521225571632,
        0.9994320869445801,
        0.026133185252547264
      ],
      [
        -0.011313852854073048,
        -0.02637806162238121,
        0.9995879530906677
      ]
    ],
    "translation": [
      -0.018121758475899696,
      0.01261541061103344,
      0.34147578477859497
    ],
    "object_normalization_center": [
      0.004299394320696592,
      0.00024249465786851943,
      0.013166682794690132
    ],
    "object_normalization_scale": [
      0.6248267889022827
    ],
    "canonical_rotation_row_matrix": [
      [
        1.0,
        0.0,
        0.0
      ],
      [
        0.0,
        1.0,
        0.0
      ],
      [
        0.0,
        0.0,
        1.0
      ]
    ],
    "canonical_yaw": [
      0.0
    ],
    "ldm106_visible_original": [
      1,
      0,
      0,
      1,
      0,
      0,
      0,
      0,
      0,
      0,
      0,
      0,
      0,
      0,
      0,
      0,
      1,
      1,
      1,
      0,
      0,
      0,
      0,
      0,
      0,
      0,
      0,
      0,
      0,
      0,
      0,
      0,
      1,
      0,
      1,
      1,
      1,
      1,
      1,
      1,
      1,
      0,
      1,
      1,
      1,
      0,
      0,
      1,
      1,
      1,
      1,
      1,
      1,
      1,
      1,
      1,
      0,
      1,
      1,
      1,
      1,
      1,
      1,
      1,
      0,
      1,
      0,
      1,
      0,
      0,
      1,
      1,
      1,
      1,
      1,
      1,
      1,
      0,
      1,
      0,
      1,
      1,
      1,
      1,
      1,
      1,
      1,
      1,
      1,
      1,
      1,
      1,
      1,
      1,
      1,
      1,
      1,
      1,
      1,
      1,
      0,
      1,
      1,
      1,
      1,
      1
    ],
    "ldm134_visible_original": [
      0,
      1,
      0,
      1,
      1,
      0,
      1,
      1,
      1,
      1,
      0,
      1,
      1,
      1,
      1,
      1,
      1,
      1,
      1,
      1,
      1,
      1,
      1,
      0,
      1,
      1,
      1,
      1,
      1,
      1,
      1,
      1,
      1,
      0,
      1,
      1,
      1,
      1,
      1,
      1,
      0,
      1,
      1,
      1,
      0,
      1,
      1,
      1,
      1,
      1,
      1,
      1,
      1,
      1,
      1,
      1,
      1,
      1,
      1,
      1,
      1,
      1,
      1,
      1,
      1,
      1,
      1,
      1,
      1,
      1,
      1,
      1,
      1,
      1,
      1,
      1,
      1,
      1,
      1,
      1,
      1,
      1,
      1,
      0,
      1,
      1,
      1,
      1,
      1,
      1,
      0,
      1,
      0,
      1,
      1,
      1,
      0,
      0,
      0,
      1,
      1,
      0,
      0,
      0,
      0,
      1,
      1,
      1,
      1,
      1,
      1,
      1,
      1,
      1,
      1,
      1,
      1,
      1,
      1,
      1,
      1,
      1,
      1,
      1,
      1,
      1,
      1,
      1,
      1,
      1,
      1,
      1,
      0,
      1
    ]
  },
  "files": {
    "ldm106_raw": "ldm106_raw.csv",
    "ldm106_aligned": "ldm106_aligned.csv",
    "ldm134_raw": "ldm134_raw.csv",
    "ldm134_aligned": "ldm134_aligned.csv",
    "metadata": "metadata.json",
    "npz": "record.npz"
  }
}