{
  "schema_version": "deeputin-calibration-seven-datasets-v7",
  "dataset_id": "person_01",
  "record_id": "frame_000212",
  "source_path": "/Users/victorkhudyakov/myproject/dataset/calibration_dataset/photos/person_01/frame_000212.jpg",
  "source_filename": "frame_000212.jpg",
  "source_sha256": "4b552d1b0400c88024b47831483820323c1e9c45dc042df9e0e298ccd0697c0b",
  "frame_index": 212,
  "sequence_id": "person_01",
  "pose": {
    "yaw": -78.91007232666016,
    "pitch": 4.14433479309082,
    "roll": -8.54317855834961
  },
  "pose_bin": "left_profile",
  "canonical_yaw": -70.0,
  "alignment": {
    "raw": "3DDFA object-space landmarks before pose/translation/camera",
    "aligned": "full-mesh normalized object-space landmarks rotated to pose-bin canonical yaw"
  },
  "arrays": {
    "angle_deg_pitch_yaw_roll": [
      4.14433479309082,
      -78.91007232666016,
      -8.54317855834961
    ],
    "rotation_row_matrix": [
      [
        0.1902150958776474,
        -0.02857440523803234,
        0.9813265204429626
      ],
      [
        0.0780334621667862,
        0.9968538284301758,
        0.013900943100452423
      ],
      [
        -0.9786362648010254,
        0.07393212616443634,
        0.19184641540050507
      ]
    ],
    "translation": [
      0.1587677001953125,
      0.02455918863415718,
      2.3825016021728516
    ],
    "object_normalization_center": [
      -0.0026406249962747097,
      0.018101926892995834,
      0.012857719324529171
    ],
    "object_normalization_scale": [
      0.6206404566764832
    ],
    "canonical_rotation_row_matrix": [
      [
        0.3420201539993286,
        0.0,
        0.9396926164627075
      ],
      [
        0.0,
        1.0,
        0.0
      ],
      [
        -0.9396926164627075,
        0.0,
        0.3420201539993286
      ]
    ],
    "canonical_yaw": [
      -70.0
    ],
    "ldm106_visible_original": [
      0,
      0,
      0,
      0,
      0,
      0,
      0,
      0,
      0,
      0,
      0,
      0,
      0,
      0,
      0,
      0,
      0,
      1,
      1,
      1,
      1,
      1,
      1,
      1,
      1,
      1,
      1,
      1,
      1,
      1,
      1,
      1,
      1,
      0,
      0,
      0,
      0,
      0,
      0,
      0,
      0,
      0,
      1,
      1,
      1,
      1,
      1,
      1,
      1,
      1,
      1,
      1,
      0,
      1,
      1,
      0,
      0,
      0,
      0,
      0,
      0,
      1,
      1,
      1,
      1,
      1,
      0,
      0,
      0,
      0,
      0,
      0,
      0,
      0,
      0,
      0,
      0,
      1,
      1,
      0,
      0,
      1,
      0,
      1,
      0,
      0,
      0,
      1,
      1,
      1,
      1,
      1,
      1,
      0,
      0,
      0,
      0,
      0,
      0,
      1,
      0,
      1,
      1,
      0,
      0,
      1
    ],
    "ldm134_visible_original": [
      0,
      0,
      0,
      0,
      0,
      0,
      0,
      0,
      0,
      0,
      0,
      0,
      0,
      0,
      0,
      0,
      0,
      0,
      0,
      0,
      0,
      0,
      0,
      1,
      0,
      1,
      0,
      1,
      1,
      1,
      0,
      0,
      0,
      0,
      1,
      1,
      1,
      1,
      1,
      0,
      0,
      0,
      0,
      0,
      0,
      0,
      0,
      0,
      0,
      0,
      0,
      0,
      0,
      0,
      0,
      0,
      0,
      1,
      1,
      1,
      1,
      1,
      1,
      1,
      1,
      1,
      1,
      1,
      1,
      1,
      0,
      0,
      0,
      0,
      0,
      0,
      0,
      0,
      1,
      1,
      1,
      1,
      1,
      1,
      1,
      1,
      1,
      0,
      0,
      0,
      0,
      0,
      0,
      0,
      0,
      0,
      1,
      1,
      1,
      1,
      1,
      0,
      0,
      0,
      0,
      0,
      0,
      0,
      0,
      0,
      1,
      1,
      1,
      1,
      1,
      1,
      1,
      1,
      0,
      0,
      0,
      0,
      0,
      0,
      0,
      1,
      0,
      1,
      1,
      1,
      1,
      1,
      1,
      1
    ]
  },
  "files": {
    "ldm106_raw": "ldm106_raw.csv",
    "ldm106_aligned": "ldm106_aligned.csv",
    "ldm134_raw": "ldm134_raw.csv",
    "ldm134_aligned": "ldm134_aligned.csv",
    "metadata": "metadata.json",
    "npz": "record.npz"
  }
}